LICENSE
eightid/__init__.py
eightid/django.py
eightid-0.1.1.dist-info/LICENSE
eightid-0.1.1.dist-info/WHEEL
eightid-0.1.1.dist-info/METADATA
eightid-0.1.1.dist-info/RECORD
