Metadata-Version: 2.1
Name: eightid
Version: 0.1.1
Summary: A short id based on 8 bytes (it fits in a PostgreSQL BigInt).
Home-page: https://github.com/barrachri/eightid
License: MIT
Keywords: eightid,guid
Author: Christian Barra
Author-email: me@christianbarra.com
Requires-Python: >=3.9,<4.0
Classifier: License :: OSI Approved :: MIT License
Classifier: Programming Language :: Python :: 3
Classifier: Programming Language :: Python :: 3.10
Classifier: Programming Language :: Python :: 3.9
Requires-Dist: Django (>=4.0.3,<5.0.0)
Project-URL: Repository, https://github.com/barrachri/eightid
